shannon/__init__.py
shannon/cli.py
shannon/client.py
shannon/errors.py
shannon/models.py
shannon/generated/orchestrator/streaming_pb2.py
shannon_sdk-0.4.2.dist-info/METADATA
shannon_sdk-0.4.2.dist-info/WHEEL
shannon_sdk-0.4.2.dist-info/entry_points.txt
shannon_sdk-0.4.2.dist-info/top_level.txt
shannon_sdk-0.4.2.dist-info/RECORD
