Metadata-Version: 2.4
Name: shannon-sdk
Version: 0.4.2
Summary: Python SDK for Shannon multi-agent AI platform
Author: Shannon Team
License: MIT
Project-URL: Homepage, https://github.com/Kocoro-lab/Shannon
Project-URL: Documentation, https://github.com/Kocoro-lab/Shannon/blob/main/clients/python/README.md
Project-URL: Repository, https://github.com/Kocoro-lab/Shannon
Project-URL: Issues, https://github.com/Kocoro-lab/Shannon/issues
Keywords: ai,agents,llm,orchestration,multi-agent,workflow
Classifier: Development Status :: 3 - Alpha
Classifier: Intended Audience :: Developers
Classifier: License :: OSI Approved :: MIT License
Classifier: Programming Language :: Python :: 3
Classifier: Programming Language :: Python :: 3.9
Classifier: Programming Language :: Python :: 3.10
Classifier: Programming Language :: Python :: 3.11
Classifier: Programming Language :: Python :: 3.12
Classifier: Topic :: Software Development :: Libraries :: Python Modules
Classifier: Topic :: Scientific/Engineering :: Artificial Intelligence
Requires-Python: >=3.9
Requires-Dist: httpx>=0.26.0
Provides-Extra: websocket
Requires-Dist: websockets>=12.0; extra == "websocket"
Provides-Extra: dev
Requires-Dist: pytest>=7.4.0; extra == "dev"
Requires-Dist: pytest-asyncio>=0.21.0; extra == "dev"
Requires-Dist: pytest-timeout>=2.2.0; extra == "dev"
Requires-Dist: pytest-cov>=4.1.0; extra == "dev"
Requires-Dist: ruff>=0.1.0; extra == "dev"
Requires-Dist: mypy>=1.7.0; extra == "dev"
Requires-Dist: build>=1.0.0; extra == "dev"
Requires-Dist: twine>=4.0.0; extra == "dev"
